datahood/__init__.py
datahood/__main__.py
datahood/_version.py
datahood/pipeline.py
datahood/cli/__init__.py
datahood/cli/export.py
datahood/cli/help_text.py
datahood/cli/schema.py
datahood/connectors/__init__.py
datahood/connectors/base.py
datahood/connectors/bson.py
datahood/connectors/mongodb.py
datahood/exporters/__init__.py
datahood/exporters/base.py
datahood/exporters/bson.py
datahood/exporters/mongodb.py
datahood/schema/__init__.py
datahood/schema/gen/__init__.py
datahood/schema/gen/base.py
datahood/schema/gen/pydantic.py
datahood/schema/gen/typeddict.py
datahood/schema/infer/__init__.py
datahood/schema/infer/base.py
datahood/schema/infer/bson.py
datahood/schema/infer/factory.py
datahood/schema/infer/mongodb.py
datahood-0.1.0.dist-info/METADATA
datahood-0.1.0.dist-info/WHEEL
datahood-0.1.0.dist-info/entry_points.txt
datahood-0.1.0.dist-info/licenses/LICENSE
datahood-0.1.0.dist-info/RECORD
