Metadata-Version: 2.4
Name: datahood
Version: 0.1.0
Summary: Small toolkit and CLI to transfer and stream data between databases using async pipelines.
Project-URL: Homepage, https://github.com/ericmiguel/datahood
Project-URL: Documentation, https://github.com/ericmiguel/datahood#readme
Project-URL: Repository, https://github.com/ericmiguel/datahood.git
Project-URL: Bug Tracker, https://github.com/ericmiguel/datahood/issues
Project-URL: Changelog, https://github.com/ericmiguel/datahood/blob/main/CHANGELOG.md
Author-email: Eric Miguel <eric.mrib@gmail.com>
Maintainer-email: Eric Miguel <eric.mrib@gmail.com>
License:                     GNU AFFERO GENERAL PUBLIC LICENSE
License-File: LICENSE
Keywords: async,database,etl,mongodb,pipeline
Classifier: Development Status :: 4 - Beta
Classifier: Environment :: Console
Classifier: Intended Audience :: Developers
Classifier: License :: OSI Approved :: GNU Affero General Public License v3
Classifier: Operating System :: OS Independent
Classifier: Programming Language :: Python :: 3
Classifier: Programming Language :: Python :: 3 :: Only
Classifier: Topic :: Software Development :: Code Generators
Classifier: Topic :: System :: Filesystems
Classifier: Topic :: Utilities
Classifier: Typing :: Typed
Requires-Python: >=3.12
Requires-Dist: aiofile>=3.9.0
Requires-Dist: motor>=3.7.1
Requires-Dist: pydantic>=2.11.9
Requires-Dist: pymongo>=4.15.0
Requires-Dist: rich>=14.1.0
Requires-Dist: typer[all]>=0.9.0
